LICENSE.txt
MANIFEST.in
README.rst
setup.py
cs_khipu.egg-info/PKG-INFO
cs_khipu.egg-info/SOURCES.txt
cs_khipu.egg-info/dependency_links.txt
cs_khipu.egg-info/not-zip-safe
cs_khipu.egg-info/requires.txt
cs_khipu.egg-info/top_level.txt
khipu/__about__.py
khipu/__init__.py
khipu/api.py
khipu/exception.py
khipu/service.py