Metadata-Version: 1.0
Name: cs-khipu
Version: 0.0.2
Summary: Unofficial Khipu Services Python SDK.
Home-page: https://github.com/cornershop/python-khipu
Author: Cornershop
Author-email: tech@cornershopapp.com
License: MIT
Platform: UNKNOWN
